cli/__init__.py
cli/main.py
eleutheria-1.1.3.dist-info/licenses/LICENSE
eleutheria-1.1.3.dist-info/METADATA
eleutheria-1.1.3.dist-info/WHEEL
eleutheria-1.1.3.dist-info/entry_points.txt
eleutheria-1.1.3.dist-info/top_level.txt
eleutheria-1.1.3.dist-info/RECORD
