Metadata-Version: 2.4
Name: eleutheria
Version: 1.1.3
Summary: Ancient Philosophy Knowledge Graph - CLI Tools
Author-email: Romain Girardi <romain.girardi@univ-cotedazur.fr>
License: CC-BY-4.0
Project-URL: Homepage, https://free-will.app
Project-URL: Repository, https://github.com/romain-girardi-eng/EleutherIA
Project-URL: Documentation, https://github.com/romain-girardi-eng/EleutherIA/tree/main/docs
Keywords: ancient-philosophy,knowledge-graph,graphrag,stoicism,free-will
Classifier: Development Status :: 4 - Beta
Classifier: Intended Audience :: Science/Research
Classifier: License :: OSI Approved
Classifier: Programming Language :: Python :: 3.11
Classifier: Programming Language :: Python :: 3.12
Classifier: Topic :: Scientific/Engineering :: Artificial Intelligence
Requires-Python: >=3.11
License-File: LICENSE
Requires-Dist: typer>=0.9.0
Requires-Dist: rich>=13.0.0
Provides-Extra: api
Requires-Dist: httpx>=0.24.0; extra == "api"
Provides-Extra: dev
Requires-Dist: pytest>=7.0.0; extra == "dev"
Requires-Dist: pytest-asyncio>=0.21.0; extra == "dev"
Requires-Dist: pytest-cov>=4.0.0; extra == "dev"
Requires-Dist: ruff>=0.1.0; extra == "dev"
Requires-Dist: mypy>=1.0.0; extra == "dev"
Dynamic: license-file
